podplay_api/__init__.py
podplay_api/cli.py
podplay_api/client.py
podplay_api/const.py
podplay_api/exceptions.py
podplay_api/models.py
podplay_api/utils.py
podplay_api-1.0.0b1.dist-info/METADATA
podplay_api-1.0.0b1.dist-info/WHEEL
podplay_api-1.0.0b1.dist-info/entry_points.txt
podplay_api-1.0.0b1.dist-info/RECORD
